CHANGELOG.txt
LICENCE.txt
MANIFEST.in
README.txt
setup.py
Offline_install/CHANGELOG.txt
Offline_install/LICENCE.txt
Offline_install/README.txt
Offline_install/__init__.py
Offline_install/setup.py
Offline_install/synproc.egg-info/SOURCES.txt
Offline_install/synproc.egg-info/dependency_links.txt
Offline_install/synproc.egg-info/requires.txt
Offline_install/synproc.egg-info/top_level.txt
my_init/__init__.py
synprocessor.egg-info/PKG-INFO
synprocessor.egg-info/SOURCES.txt
synprocessor.egg-info/dependency_links.txt
synprocessor.egg-info/requires.txt
synprocessor.egg-info/top_level.txt