Metadata-Version: 2.1
Name: synprocessor
Version: 0.0.1
Summary: A SYN file converting tool
Home-page: UNKNOWN
Author: Abdelhadi Harrouz
Author-email: abdelhadiharrouz@outlook.com
License: MIT
Platform: UNKNOWN
Classifier: Development Status :: 5 - Production/Stable
Classifier: Intended Audience :: Education
Classifier: License :: OSI Approved :: MIT License
License-File: LICENCE.txt
